CHANGES.txt
LICENSE.txt
MANIFEST.in
README.rst
setup.py
Pykaboo.egg-info/PKG-INFO
Pykaboo.egg-info/SOURCES.txt
Pykaboo.egg-info/dependency_links.txt
Pykaboo.egg-info/entry_points.txt
Pykaboo.egg-info/requires.txt
Pykaboo.egg-info/top_level.txt
pykaboo/__init__.py
pykaboo/pykaboo_style.css