Metadata-Version: 1.0
Name: Pykaboo
Version: 0.1.2
Summary: A python source viewer.
Home-page: http://pykaboo.herokuapp.com
Author: Robrecht De Rouck
Author-email: Robrecht.De.Rouck@gmail.com
License: Modified BSD license
Platform: UNKNOWN
